odoo/addons/web_widget_child_selector/README.rst
odoo/addons/web_widget_child_selector/__init__.py
odoo/addons/web_widget_child_selector/__manifest__.py
odoo/addons/web_widget_child_selector/i18n/web_widget_child_selector.pot
odoo/addons/web_widget_child_selector/models/__init__.py
odoo/addons/web_widget_child_selector/models/base.py
odoo/addons/web_widget_child_selector/readme/CONTRIBUTORS.rst
odoo/addons/web_widget_child_selector/readme/DESCRIPTION.rst
odoo/addons/web_widget_child_selector/readme/USAGE.rst
odoo/addons/web_widget_child_selector/static/description/edit_mode.png
odoo/addons/web_widget_child_selector/static/description/icon.png
odoo/addons/web_widget_child_selector/static/description/index.html
odoo/addons/web_widget_child_selector/static/src/js/widget_child_selector.js
odoo/addons/web_widget_child_selector/static/src/less/widget_child_selector.less
odoo/addons/web_widget_child_selector/static/src/xml/widget_child_selector.xml
odoo/addons/web_widget_child_selector/tests/__init__.py
odoo/addons/web_widget_child_selector/tests/test_widget_child_selector.py
odoo/addons/web_widget_child_selector/views/assets.xml
odoo11_addon_web_widget_child_selector-11.0.1.0.1.dist-info/METADATA
odoo11_addon_web_widget_child_selector-11.0.1.0.1.dist-info/WHEEL
odoo11_addon_web_widget_child_selector-11.0.1.0.1.dist-info/top_level.txt
odoo11_addon_web_widget_child_selector-11.0.1.0.1.dist-info/RECORD
